AUTHORS.rst
CONTRIBUTING.rst
HISTORY.rst
LICENSE
MANIFEST.in
README.rst
setup.cfg
setup.py
docs/Makefile
docs/authors.rst
docs/conf.py
docs/contributing.rst
docs/history.rst
docs/index.rst
docs/installation.rst
docs/make.bat
docs/readme.rst
docs/usage.rst
publish/__init__.py
publish/publish.py
publish2cloud.egg-info/PKG-INFO
publish2cloud.egg-info/SOURCES.txt
publish2cloud.egg-info/dependency_links.txt
publish2cloud.egg-info/entry_points.txt
publish2cloud.egg-info/not-zip-safe
publish2cloud.egg-info/requires.txt
publish2cloud.egg-info/top_level.txt
tests/__init__.py
tests/test_publish.py