Metadata-Version: 1.1
Name: publish2cloud
Version: 0.1.1
Summary: publish your site to qiniu.com
Home-page: https://github.com/wwj718/publish
Author: wenjiewu
Author-email: wuwenjie718@gmail.com
License: BSD license
Keywords: publish
Platform: UNKNOWN
Classifier: Development Status :: 2 - Pre-Alpha
Classifier: Intended Audience :: Developers
Classifier: License :: OSI Approved :: BSD License
Classifier: Natural Language :: English
Classifier: Programming Language :: Python :: 2
Classifier: Programming Language :: Python :: 2.6
Classifier: Programming Language :: Python :: 2.7
Classifier: Programming Language :: Python :: 3
Classifier: Programming Language :: Python :: 3.3
Classifier: Programming Language :: Python :: 3.4
Classifier: Programming Language :: Python :: 3.5
